serializetool/__init__.py
serializetool/serialize.py
serializetool-0.1.dist-info/METADATA
serializetool-0.1.dist-info/WHEEL
serializetool-0.1.dist-info/top_level.txt
serializetool-0.1.dist-info/RECORD
