Metadata-Version: 2.1
Name: serializetool
Version: 0.1
Summary: Yolo model serialize
License: MIT License
Requires-Python: >=3.7
